{
  "id": "6acd8f6a-d687-40ac-8a70-458e5dfd2607",
  "prevId": "cfc6f30e-244e-4003-a412-11937e3c1a3e",
  "version": "7",
  "dialect": "postgresql",
  "tables": {
    "public.budget": {
      "name": "budget",
      "schema": "",
      "columns": {
        "id": {
          "name": "id",
          "type": "serial",
          "primaryKey": true,
          "notNull": true
        },
        "createdAt": {
          "name": "createdAt",
          "type": "timestamp",
          "primaryKey": false,
          "notNull": false,
          "default": "now()"
        },
        "updatedAt": {
          "name": "updatedAt",
          "type": "timestamp",
          "primaryKey": false,
          "notNull": false,
          "default": "now()"
        },
        "amount": {
          "name": "amount",
          "type": "integer",
          "primaryKey": false,
          "notNull": true
        },
        "name": {
          "name": "name",
          "type": "text",
          "primaryKey": false,
          "notNull": true
        },
        "teamId": {
          "name": "teamId",
          "type": "integer",
          "primaryKey": false,
          "notNull": false
        },
        "validFrom": {
          "name": "validFrom",
          "type": "timestamp",
          "primaryKey": false,
          "notNull": true
        },
        "validUntil": {
          "name": "validUntil",
          "type": "timestamp",
          "primaryKey": false,
          "notNull": true
        }
      },
      "indexes": {},
      "foreignKeys": {
        "budget_teamId_team_id_fk": {
          "name": "budget_teamId_team_id_fk",
          "tableFrom": "budget",
          "columnsFrom": [
            "teamId"
          ],
          "tableTo": "team",
          "columnsTo": [
            "id"
          ],
          "onUpdate": "no action",
          "onDelete": "no action"
        }
      },
      "compositePrimaryKeys": {},
      "uniqueConstraints": {},
      "policies": {},
      "checkConstraints": {},
      "isRLSEnabled": false
    },
    "public.member": {
      "name": "member",
      "schema": "",
      "columns": {
        "id": {
          "name": "id",
          "type": "serial",
          "primaryKey": true,
          "notNull": true
        },
        "createdAt": {
          "name": "createdAt",
          "type": "timestamp",
          "primaryKey": false,
          "notNull": false,
          "default": "now()"
        },
        "updatedAt": {
          "name": "updatedAt",
          "type": "timestamp",
          "primaryKey": false,
          "notNull": false,
          "default": "now()"
        },
        "name": {
          "name": "name",
          "type": "text",
          "primaryKey": false,
          "notNull": true
        },
        "teamId": {
          "name": "teamId",
          "type": "integer",
          "primaryKey": false,
          "notNull": false
        },
        "userId": {
          "name": "userId",
          "type": "uuid",
          "primaryKey": false,
          "notNull": false
        }
      },
      "indexes": {},
      "foreignKeys": {
        "member_teamId_team_id_fk": {
          "name": "member_teamId_team_id_fk",
          "tableFrom": "member",
          "columnsFrom": [
            "teamId"
          ],
          "tableTo": "team",
          "columnsTo": [
            "id"
          ],
          "onUpdate": "no action",
          "onDelete": "no action"
        },
        "member_userId_users_id_fk": {
          "name": "member_userId_users_id_fk",
          "tableFrom": "member",
          "columnsFrom": [
            "userId"
          ],
          "tableTo": "users",
          "schemaTo": "auth",
          "columnsTo": [
            "id"
          ],
          "onUpdate": "no action",
          "onDelete": "cascade"
        }
      },
      "compositePrimaryKeys": {},
      "uniqueConstraints": {},
      "policies": {},
      "checkConstraints": {},
      "isRLSEnabled": false
    },
    "public.purchase": {
      "name": "purchase",
      "schema": "",
      "columns": {
        "id": {
          "name": "id",
          "type": "serial",
          "primaryKey": true,
          "notNull": true
        },
        "createdAt": {
          "name": "createdAt",
          "type": "timestamp",
          "primaryKey": false,
          "notNull": false,
          "default": "now()"
        },
        "updatedAt": {
          "name": "updatedAt",
          "type": "timestamp",
          "primaryKey": false,
          "notNull": false,
          "default": "now()"
        },
        "amount": {
          "name": "amount",
          "type": "integer",
          "primaryKey": false,
          "notNull": true
        },
        "budgetId": {
          "name": "budgetId",
          "type": "integer",
          "primaryKey": false,
          "notNull": false
        },
        "teamId": {
          "name": "teamId",
          "type": "integer",
          "primaryKey": false,
          "notNull": false
        }
      },
      "indexes": {},
      "foreignKeys": {
        "purchase_budgetId_budget_id_fk": {
          "name": "purchase_budgetId_budget_id_fk",
          "tableFrom": "purchase",
          "columnsFrom": [
            "budgetId"
          ],
          "tableTo": "budget",
          "columnsTo": [
            "id"
          ],
          "onUpdate": "no action",
          "onDelete": "no action"
        },
        "purchase_teamId_team_id_fk": {
          "name": "purchase_teamId_team_id_fk",
          "tableFrom": "purchase",
          "columnsFrom": [
            "teamId"
          ],
          "tableTo": "team",
          "columnsTo": [
            "id"
          ],
          "onUpdate": "no action",
          "onDelete": "no action"
        }
      },
      "compositePrimaryKeys": {},
      "uniqueConstraints": {},
      "policies": {},
      "checkConstraints": {},
      "isRLSEnabled": false
    },
    "public.team": {
      "name": "team",
      "schema": "",
      "columns": {
        "id": {
          "name": "id",
          "type": "serial",
          "primaryKey": true,
          "notNull": true
        },
        "createdAt": {
          "name": "createdAt",
          "type": "timestamp",
          "primaryKey": false,
          "notNull": false,
          "default": "now()"
        },
        "updatedAt": {
          "name": "updatedAt",
          "type": "timestamp",
          "primaryKey": false,
          "notNull": false,
          "default": "now()"
        },
        "email": {
          "name": "email",
          "type": "text",
          "primaryKey": false,
          "notNull": true
        },
        "name": {
          "name": "name",
          "type": "text",
          "primaryKey": false,
          "notNull": false
        }
      },
      "indexes": {},
      "foreignKeys": {},
      "compositePrimaryKeys": {},
      "uniqueConstraints": {},
      "policies": {},
      "checkConstraints": {},
      "isRLSEnabled": false
    }
  },
  "enums": {},
  "schemas": {},
  "views": {},
  "sequences": {},
  "roles": {},
  "policies": {},
  "_meta": {
    "columns": {},
    "schemas": {},
    "tables": {}
  }
}